torchprofile/__init__.py
torchprofile/handlers.py
torchprofile/profile.py
torchprofile/version.py
torchprofile/utils/__init__.py
torchprofile/utils/flatten.py
torchprofile/utils/math.py
torchprofile/utils/trace.py
torchprofile/utils/ir/__init__.py
torchprofile/utils/ir/graph.py
torchprofile/utils/ir/node.py
torchprofile/utils/ir/variable.py
torchprofile-0.0.4.dist-info/LICENSE
torchprofile-0.0.4.dist-info/METADATA
torchprofile-0.0.4.dist-info/WHEEL
torchprofile-0.0.4.dist-info/top_level.txt
torchprofile-0.0.4.dist-info/RECORD
