Metadata-Version: 2.1
Name: torchprofile
Version: 0.0.4
Summary: UNKNOWN
Home-page: https://github.com/zhijian-liu/torchprofile/
Author: UNKNOWN
Author-email: UNKNOWN
License: MIT
Platform: UNKNOWN
Requires-Dist: numpy (>=1.14)
Requires-Dist: torch (>=1.4)
Requires-Dist: torchvision (>=0.4)
